computed_cached_property/__init__.py
computed_cached_property/base.py
computed_cached_property-0.0.3.dist-info/LICENSE
computed_cached_property-0.0.3.dist-info/METADATA
computed_cached_property-0.0.3.dist-info/WHEEL
computed_cached_property-0.0.3.dist-info/top_level.txt
computed_cached_property-0.0.3.dist-info/RECORD
