Metadata-Version: 2.1
Name: computed-cached-property
Version: 0.0.3
Summary: A decorator for caching computed properties in classes. like Vue's Computed-Properties
Home-page: https://github.com/lisonge/computed-cached-property
Author: Li Songe
Author-email: i@songe.li
License: MIT
Keywords: cached-property
Platform: UNKNOWN
Classifier: Programming Language :: Python :: 3
Classifier: License :: OSI Approved :: MIT License
Classifier: Operating System :: OS Independent
Requires-Python: >=3.6
